bucketman/__init__.py
bucketman/app.py
bucketman/bucketman.tcss
bucketman/cli.py
bucketman/constants.py
bucketman/modals.py
bucketman/widgets/__init__.py
bucketman/widgets/common.py
bucketman/widgets/localtree.py
bucketman/widgets/s3tree.py
bucketman-0.3.1.dist-info/METADATA
bucketman-0.3.1.dist-info/WHEEL
bucketman-0.3.1.dist-info/entry_points.txt
bucketman-0.3.1.dist-info/top_level.txt
bucketman-0.3.1.dist-info/RECORD
