Metadata-Version: 2.1
Name: bucketman
Version: 0.3.1
Summary: A terminal application for working with S3 buckets.
Home-page: UNKNOWN
License: UNKNOWN
Platform: UNKNOWN
Requires-Dist: boto3 ==1.28.54
Requires-Dist: click ==8.1.7
Requires-Dist: textual ==0.38.1
Provides-Extra: dev
Requires-Dist: autopep8 ; extra == 'dev'
Requires-Dist: wheel ; extra == 'dev'
Requires-Dist: pylint ; extra == 'dev'
Requires-Dist: keepachangelog ; extra == 'dev'
